Metadata-Version: 1.0
Name: python-randomword-fr
Version: 1.0.0
Summary: Cool simple Python module to get random French words with definition (offline usage - French words and definitions)
Home-page: https://github.com/remaudcorentin-dev/python-randomword-fr
Author: Corentin Remaud
Author-email: remaudcorentin.dev@gmail.com
License: MIT
Platform: UNKNOWN
